tstrprocess-0.1.0.dev3.dist-info/METADATA
tstrprocess-0.1.0.dev3.dist-info/WHEEL
tstrprocess-0.1.0.dev3.dist-info/entry_points.txt
tstrprocess-0.1.0.dev3.dist-info/licenses/LICENSE
tstrprocess/__init__.py
tstrprocess-0.1.0.dev3.dist-info/RECORD
