Metadata-Version: 2.1
Name: tstrprocess
Version: 0.1.0.dev3
Summary: t-string based subprocess invocation
Author-Email: Alyssa Coghlan <ncoghlan@gmail.com>, Nick Humrich <nick@humrich.us>
License: MIT
Project-URL: Homepage, https://github.com/ncoghlan/tstrprocess
Project-URL: Issues, https://github.com/ncoghlan/tstrprocess/issues
Requires-Python: >=3.13
Requires-Dist: plumbum>=1.9.0
